servciceberg/__init__.py
servciceberg/config.py
servciceberg-1.0.0.dist-info/LICENSE
servciceberg-1.0.0.dist-info/METADATA
servciceberg-1.0.0.dist-info/WHEEL
servciceberg-1.0.0.dist-info/top_level.txt
servciceberg-1.0.0.dist-info/RECORD
