Metadata-Version: 2.1
Name: servciceberg
Version: 1.0.0
Summary: Server implmentation of services for python
Author-email: Yusuf Ali <ali@yusuf.email>
Project-URL: Homepage, https://github.com/serv-c/servc-iceberg
Project-URL: Bug Tracker, https://github.com/serv-c/servc-iceberg/issues
Classifier: Programming Language :: Python :: 3
Classifier: License :: OSI Approved :: MIT License
Classifier: Operating System :: OS Independent
Requires-Python: >=3.11
License-File: LICENSE
